easylib/__init__.py
easylib/dl/__init__.py
easylib/dl/keras_model_runner.py
easylib/dl/keras_model_runner_test.py
easylib/io/__init__.py
easylib/io/file_merger.py
easylib/io/file_merger_test.py
easylib/io/file_reader.py
easylib/io/file_reader_test.py
easylib/io/file_spliter.py
easylib/io/file_spliter_test.py
easylib/log/__init__.py
easylib/log/logger_initializer.py
easylib/log/logger_initializer_test.py
easylib/nlp/__init__.py
easylib/nlp/vocabs.py
easylib/nlp/vocabs_test.py
easylib-0.1.0.dist-info/LICENSE
easylib-0.1.0.dist-info/METADATA
easylib-0.1.0.dist-info/WHEEL
easylib-0.1.0.dist-info/top_level.txt
easylib-0.1.0.dist-info/RECORD
