Metadata-Version: 2.1
Name: easylib
Version: 0.1.0
Summary: Frequently used functions and modules library for Python 3 by ZhouYang Luo.
Home-page: https://github.com/luozhouyang/easylib
Author: ZhouYang Luo
Author-email: zhouyang.luo@gmail.com
License: UNKNOWN
Platform: UNKNOWN
Classifier: Programming Language :: Python :: 3.6
Classifier: License :: OSI Approved :: Apache Software License
Classifier: Operating System :: OS Independent
